{
    "name": "dsa5-communitysoundconfig",
    "title": "The Dark Eye 5th Ed. - Community Sound Config",
    "description": "Configuration files for sounds connected to abilites.",
    "author": "Plushtoast",
    "version": "1.0.2",
    "systems": ["dsa5"],
    "minimumCoreVersion": "0.8.5",
    "compatibleCoreVersion": "0.8.6",
    "url": "https://github.com/Plushtoast/dsa5-communitysoundconfig",
    "manifest": "https://raw.githubusercontent.com/Plushtoast/dsa5-communitysoundconfig/master/module.json",
    "download": "https://github.com/Plushtoast/dsa5-communitysoundconfig/archive/master.zip",
    "languages": [{
        "lang": "de",
        "name": "Deutsch",
        "path": "lang/de.json"
    }, {
        "lang": "en",
        "name": "English",
        "path": "lang/en.json"
    }],
    "dependencies": [{
        "name": "dsa5",
        "type": "system"
    }],
    "esmodules": [
        "modules/init.js"
    ],
    "packs": []
}
